{
  "id": "QnulIj0SVRIABYIU",
  "name": "Webhook 8",
  "nodes": [
    {
      "parameters": {
        "path": "8774358d-7b64-47fc-bd94-e9e0bd4f1bd5",
        "options": {}
      },
      "type": "n8n-nodes-base.webhook",
      "typeVersion": 2.1,
      "position": [
        0,
        0
      ],
      "id": "adf963f1-a9ec-460d-8834-2fd3f8d97aea",
      "name": "Webhook",
      "webhookId": "8774358d-7b64-47fc-bd94-e9e0bd4f1bd5"
    }
  ],
  "connections": {},
  "settings": {
    "executionOrder": "v1"
  },
  "triggerCount": 1,
  "versionId": "02ed8ca1-b987-4fd9-88c1-ad16044c31db",
  "owner": {
    "type": "team",
    "teamId": "T9saDFOxSaQMzwBC",
    "teamName": "MCP Test"
  },
  "parentFolderId": "2qf9iizxtLyeqO4q",
  "isArchived": false
}